dbconnectionretrier/__init__.py
dbconnectionretrier/apps.py
dbconnectionretrier/ensure_connection.py
dbconnectionretrier/patch.py
django_db_connection_retrier-1.0.dist-info/LICENSE
django_db_connection_retrier-1.0.dist-info/METADATA
django_db_connection_retrier-1.0.dist-info/WHEEL
django_db_connection_retrier-1.0.dist-info/top_level.txt
django_db_connection_retrier-1.0.dist-info/RECORD
