Metadata-Version: 2.1
Name: django-db-connection-retrier
Version: 1.0
Summary: Automatically ty re-establishing the Django database connection when it gets lost.
Home-page: https://github.com/SectorLabs/django-db-connection-retrier
Author: Sector Labs
Author-email: open-source@sectorlabs.ro
License: MIT License
Keywords: django,postgres,extra,hstore,ltree
Platform: UNKNOWN
Classifier: Environment :: Web Environment
Classifier: Framework :: Django
Classifier: Intended Audience :: Developers
Classifier: License :: OSI Approved :: MIT License
Classifier: Operating System :: OS Independent
Classifier: Programming Language :: Python
Classifier: Programming Language :: Python :: 3.5
License-File: LICENSE
